<?xml version="1.0" encoding="UTF-8"?>
<krpano version="1.19"
        onstart="startup"
        logkey="false"
        bgcolor="#ffffff"
        projectfloorplanurl=""
        projecttitleid="project_title"
        projectdescriptionid="">


  <security cors="">
    <!--
    <crossdomainxml url="http://RESSOURCES_URL/crossdomain.xml" />
    -->
    <allowdomain domain="*" />
  </security>

  <krpano tour_firststartactiondone="false" />
  <events name="startbehavioursevents" onxmlcomplete="startbehavioursxmlcompleteaction();" keep="true"/>

  <!-- generated by Panotour Pro V2.5.9 64bits : 30-06-2018 19-07-42 -->
  <!-- Project file : /Users/ioannisexarchos/Desktop/Crowdhackathon VR /VRCrowdHackathon/VRcrowdhackathon.kpt -->
  <!-- Plugins and Spot Styles -->
  <include url="%FIRSTXML%/vr_skin_vr.xml"/>
  <!-- Core actions -->
  <include url="%FIRSTXML%/vr_core_vr.xml"/>
  <!-- Tour Messages -->
  <include url="%FIRSTXML%/vr_messages_en.xml"/>

  <action name="startup">

    if (s !== null, if (startscene === null OR startscene === "undefined", set(startscene, get(s));); );
    if (startscene === null OR startscene === "undefined",
      set(startscene, pano4036);
    );
    if(startlanguage !== null AND startlanguage !== "undefined",
      set(tour_language, get(startlanguage));
    );
    if(scene[get(startscene)].full360,
    mainloadsceneStartup(get(startscene));
    if (h !== null,
      if (v !== null,
        if (f !== null,
          lookat(get(h), get(v), get(f));
         ,
          lookat(get(h), get(v));
        );
      ,
        if (f !== null,
          lookat(get(h), get(view.vlookat), get(f));
         ,
          lookat(get(h), get(view.vlookat));
        );
      );
    ,
      if (v !== null,
        if (f !== null,
          lookat(get(view.hlookat), get(v), get(f));
         ,
          lookat(get(view.hlookat), get(v));
        );
      ,
        if (f !== null,
          lookat(get(view.hlookat), get(view.vlookat), get(f));
        );
      );
    );
    );
  </action>

  <!-- 4 Groups -->
  <panoramagroup name="panogroup4049"
                 mainscene="pano4036"
                 color="808080"
                 alpha="1"
                 thumburl="%FIRSTXML%/crowhackathon_6_4036/thumbnail.jpg"
                 floorplanurl=""
                 titleid="panogroup4049_title"
                 descriptionid=""/>
  <panoramagroup name="panogroup4051"
                 mainscene="pano4038"
                 color="808080"
                 alpha="1"
                 thumburl="%FIRSTXML%/elevetor_to_1_or_5a_4038/thumbnail.jpg"
                 floorplanurl=""
                 titleid="panogroup4051_title"
                 descriptionid=""/>
  <panoramagroup name="panogroup4054"
                 mainscene="pano4041"
                 color="808080"
                 alpha="1"
                 thumburl="%FIRSTXML%/nationalopera_4041/thumbnail.jpg"
                 floorplanurl=""
                 titleid="panogroup4054_title"
                 descriptionid=""/>
  <panoramagroup name="panogroup4052"
                 mainscene="pano4039"
                 color="808080"
                 alpha="1"
                 thumburl="%FIRSTXML%/first_floor_4039/thumbnail.jpg"
                 floorplanurl=""
                 titleid="panogroup4052_title"
                 descriptionid=""/>

  <!-- Group 5A CrowdHackathon : 5 panoramas -->
  

<!-- **** @PanoName="Crowhackathon-6" @PanoFile="/Users/ioannisexarchos/Desktop/Crowdhackathon VR /smartcity/Crowhackathon-6.jpg" **** -->
<!-- **** Width="6912px" Height="3456px" **** -->
<scene name="pano4036"
       heading="0"
       group="panogroup4049"
       thumburl="%FIRSTXML%/crowhackathon_6_4036/thumbnail.jpg"
       backgroundsound=""
       backgroundsoundloops="0"
       haspolygons="false"
       titleid="pano4036_title"
       descriptionid=""
       multires="true"
       planar="false"
       full360="true"
       video="false"
       seen="false">

    <autorotate horizon="0.000000" tofov="90.000000" waittime="1" speed="5"/>


    <panoview h="0.000000" v="0.000000" fov="90.000000" hmin="-180" hmax="180" vmin="-90" vmax="90" fovmax="90" />

    <view fisheye="0"
          limitview="range"
          hlookatmin="-180"
          hlookatmax="180"
          vlookatmin="-90"
          vlookatmax="90"
          maxpixelzoom="1.0"
          fovtype="VFOV"
          fovmax="90"
          fov="90.000000"
          hlookat="0.000000"
          vlookat="0.000000"/>

    <preview url="%FIRSTXML%/crowhackathon_6_4036/preview.jpg" type="CUBESTRIP" striporder="FRBLUD" />

    <image type="CUBE" multires="true" baseindex="0" tilesize="512" devices="!androidstock|webgl">
      <level tiledimagewidth="2560" tiledimageheight="2560">
          <front url="crowhackathon_6_4036/0/2/%v_%u.jpg"/>
          <right url="crowhackathon_6_4036/1/2/%v_%u.jpg"/>
          <back  url="crowhackathon_6_4036/2/2/%v_%u.jpg"/>
          <left  url="crowhackathon_6_4036/3/2/%v_%u.jpg"/>
          <up    url="crowhackathon_6_4036/4/2/%v_%u.jpg"/>
          <down  url="crowhackathon_6_4036/5/2/%v_%u.jpg"/>
      </level>
      <level tiledimagewidth="1536" tiledimageheight="1536">
          <front url="crowhackathon_6_4036/0/1/%v_%u.jpg"/>
          <right url="crowhackathon_6_4036/1/1/%v_%u.jpg"/>
          <back  url="crowhackathon_6_4036/2/1/%v_%u.jpg"/>
          <left  url="crowhackathon_6_4036/3/1/%v_%u.jpg"/>
          <up    url="crowhackathon_6_4036/4/1/%v_%u.jpg"/>
          <down  url="crowhackathon_6_4036/5/1/%v_%u.jpg"/>
      </level>
      <level tiledimagewidth="1024" tiledimageheight="1024">
          <front url="crowhackathon_6_4036/0/0/%v_%u.jpg"/>
          <right url="crowhackathon_6_4036/1/0/%v_%u.jpg"/>
          <back  url="crowhackathon_6_4036/2/0/%v_%u.jpg"/>
          <left  url="crowhackathon_6_4036/3/0/%v_%u.jpg"/>
          <up    url="crowhackathon_6_4036/4/0/%v_%u.jpg"/>
          <down  url="crowhackathon_6_4036/5/0/%v_%u.jpg"/>
      </level>
    </image>
      <image type="CUBE" devices="androidstock.and.no-webgl">
        <front url="crowhackathon_6_4036/mobile/0.jpg"/>
        <right url="crowhackathon_6_4036/mobile/1.jpg"/>
        <back  url="crowhackathon_6_4036/mobile/2.jpg"/>
        <left  url="crowhackathon_6_4036/mobile/3.jpg"/>
        <up    url="crowhackathon_6_4036/mobile/4.jpg"/>
        <down  url="crowhackathon_6_4036/mobile/5.jpg"/>
      </image>








  <action name="setzorder2onstandardspots">
    if (device.html5,
      ifnot (device.desktop,


      );
    );
  </action>


</scene>



<!-- **** @PanoName="Open Area" @PanoFile="/Users/ioannisexarchos/Desktop/Crowdhackathon VR /smartcity/Open Area.jpg" **** -->
<!-- **** Width="6912px" Height="3456px" **** -->
<scene name="pano4042"
       heading="0"
       group="panogroup4049"
       thumburl="%FIRSTXML%/open_area_4042/thumbnail.jpg"
       backgroundsound=""
       backgroundsoundloops="0"
       haspolygons="false"
       titleid="pano4042_title"
       descriptionid=""
       multires="true"
       planar="false"
       full360="true"
       video="false"
       seen="false">

    <autorotate horizon="0.000000" tofov="90.000000" waittime="1" speed="5"/>


    <panoview h="0.000000" v="0.000000" fov="90.000000" hmin="-180" hmax="180" vmin="-90" vmax="90" fovmax="90" />

    <view fisheye="0"
          limitview="range"
          hlookatmin="-180"
          hlookatmax="180"
          vlookatmin="-90"
          vlookatmax="90"
          maxpixelzoom="1.0"
          fovtype="VFOV"
          fovmax="90"
          fov="90.000000"
          hlookat="0.000000"
          vlookat="0.000000"/>

    <preview url="%FIRSTXML%/open_area_4042/preview.jpg" type="CUBESTRIP" striporder="FRBLUD" />

    <image type="CUBE" multires="true" baseindex="0" tilesize="512" devices="!androidstock|webgl">
      <level tiledimagewidth="2560" tiledimageheight="2560">
          <front url="open_area_4042/0/2/%v_%u.jpg"/>
          <right url="open_area_4042/1/2/%v_%u.jpg"/>
          <back  url="open_area_4042/2/2/%v_%u.jpg"/>
          <left  url="open_area_4042/3/2/%v_%u.jpg"/>
          <up    url="open_area_4042/4/2/%v_%u.jpg"/>
          <down  url="open_area_4042/5/2/%v_%u.jpg"/>
      </level>
      <level tiledimagewidth="1536" tiledimageheight="1536">
          <front url="open_area_4042/0/1/%v_%u.jpg"/>
          <right url="open_area_4042/1/1/%v_%u.jpg"/>
          <back  url="open_area_4042/2/1/%v_%u.jpg"/>
          <left  url="open_area_4042/3/1/%v_%u.jpg"/>
          <up    url="open_area_4042/4/1/%v_%u.jpg"/>
          <down  url="open_area_4042/5/1/%v_%u.jpg"/>
      </level>
      <level tiledimagewidth="1024" tiledimageheight="1024">
          <front url="open_area_4042/0/0/%v_%u.jpg"/>
          <right url="open_area_4042/1/0/%v_%u.jpg"/>
          <back  url="open_area_4042/2/0/%v_%u.jpg"/>
          <left  url="open_area_4042/3/0/%v_%u.jpg"/>
          <up    url="open_area_4042/4/0/%v_%u.jpg"/>
          <down  url="open_area_4042/5/0/%v_%u.jpg"/>
      </level>
    </image>
      <image type="CUBE" devices="androidstock.and.no-webgl">
        <front url="open_area_4042/mobile/0.jpg"/>
        <right url="open_area_4042/mobile/1.jpg"/>
        <back  url="open_area_4042/mobile/2.jpg"/>
        <left  url="open_area_4042/mobile/3.jpg"/>
        <up    url="open_area_4042/mobile/4.jpg"/>
        <down  url="open_area_4042/mobile/5.jpg"/>
      </image>








  <action name="setzorder2onstandardspots">
    if (device.html5,
      ifnot (device.desktop,


      );
    );
  </action>


</scene>



<!-- **** @PanoName="Crowhackathon-7" @PanoFile="/Users/ioannisexarchos/Desktop/Crowdhackathon VR /smartcity/Crowhackathon-7.jpg" **** -->
<!-- **** Width="6912px" Height="3456px" **** -->
<scene name="pano4037"
       heading="0"
       group="panogroup4049"
       thumburl="%FIRSTXML%/crowhackathon_7_4037/thumbnail.jpg"
       backgroundsound=""
       backgroundsoundloops="0"
       haspolygons="false"
       titleid="pano4037_title"
       descriptionid=""
       multires="true"
       planar="false"
       full360="true"
       video="false"
       seen="false">

    <autorotate horizon="0.000000" tofov="90.000000" waittime="1" speed="5"/>


    <panoview h="0.000000" v="0.000000" fov="90.000000" hmin="-180" hmax="180" vmin="-90" vmax="90" fovmax="90" />

    <view fisheye="0"
          limitview="range"
          hlookatmin="-180"
          hlookatmax="180"
          vlookatmin="-90"
          vlookatmax="90"
          maxpixelzoom="1.0"
          fovtype="VFOV"
          fovmax="90"
          fov="90.000000"
          hlookat="0.000000"
          vlookat="0.000000"/>

    <preview url="%FIRSTXML%/crowhackathon_7_4037/preview.jpg" type="CUBESTRIP" striporder="FRBLUD" />

    <image type="CUBE" multires="true" baseindex="0" tilesize="512" devices="!androidstock|webgl">
      <level tiledimagewidth="2560" tiledimageheight="2560">
          <front url="crowhackathon_7_4037/0/2/%v_%u.jpg"/>
          <right url="crowhackathon_7_4037/1/2/%v_%u.jpg"/>
          <back  url="crowhackathon_7_4037/2/2/%v_%u.jpg"/>
          <left  url="crowhackathon_7_4037/3/2/%v_%u.jpg"/>
          <up    url="crowhackathon_7_4037/4/2/%v_%u.jpg"/>
          <down  url="crowhackathon_7_4037/5/2/%v_%u.jpg"/>
      </level>
      <level tiledimagewidth="1536" tiledimageheight="1536">
          <front url="crowhackathon_7_4037/0/1/%v_%u.jpg"/>
          <right url="crowhackathon_7_4037/1/1/%v_%u.jpg"/>
          <back  url="crowhackathon_7_4037/2/1/%v_%u.jpg"/>
          <left  url="crowhackathon_7_4037/3/1/%v_%u.jpg"/>
          <up    url="crowhackathon_7_4037/4/1/%v_%u.jpg"/>
          <down  url="crowhackathon_7_4037/5/1/%v_%u.jpg"/>
      </level>
      <level tiledimagewidth="1024" tiledimageheight="1024">
          <front url="crowhackathon_7_4037/0/0/%v_%u.jpg"/>
          <right url="crowhackathon_7_4037/1/0/%v_%u.jpg"/>
          <back  url="crowhackathon_7_4037/2/0/%v_%u.jpg"/>
          <left  url="crowhackathon_7_4037/3/0/%v_%u.jpg"/>
          <up    url="crowhackathon_7_4037/4/0/%v_%u.jpg"/>
          <down  url="crowhackathon_7_4037/5/0/%v_%u.jpg"/>
      </level>
    </image>
      <image type="CUBE" devices="androidstock.and.no-webgl">
        <front url="crowhackathon_7_4037/mobile/0.jpg"/>
        <right url="crowhackathon_7_4037/mobile/1.jpg"/>
        <back  url="crowhackathon_7_4037/mobile/2.jpg"/>
        <left  url="crowhackathon_7_4037/mobile/3.jpg"/>
        <up    url="crowhackathon_7_4037/mobile/4.jpg"/>
        <down  url="crowhackathon_7_4037/mobile/5.jpg"/>
      </image>








  <action name="setzorder2onstandardspots">
    if (device.html5,
      ifnot (device.desktop,


      );
    );
  </action>


</scene>



<!-- **** @PanoName="Center" @PanoFile="/Users/ioannisexarchos/Desktop/Crowdhackathon VR /smartcity/Center.jpg" **** -->
<!-- **** Width="6912px" Height="3456px" **** -->
<scene name="pano4035"
       heading="0"
       group="panogroup4049"
       thumburl="%FIRSTXML%/center_4035/thumbnail.jpg"
       backgroundsound=""
       backgroundsoundloops="0"
       haspolygons="false"
       titleid="pano4035_title"
       descriptionid=""
       multires="true"
       planar="false"
       full360="true"
       video="false"
       seen="false">

    <autorotate horizon="0.000000" tofov="90.000000" waittime="1" speed="5"/>


    <panoview h="0.000000" v="0.000000" fov="90.000000" hmin="-180" hmax="180" vmin="-90" vmax="90" fovmax="90" />

    <view fisheye="0"
          limitview="range"
          hlookatmin="-180"
          hlookatmax="180"
          vlookatmin="-90"
          vlookatmax="90"
          maxpixelzoom="1.0"
          fovtype="VFOV"
          fovmax="90"
          fov="90.000000"
          hlookat="0.000000"
          vlookat="0.000000"/>

    <preview url="%FIRSTXML%/center_4035/preview.jpg" type="CUBESTRIP" striporder="FRBLUD" />

    <image type="CUBE" multires="true" baseindex="0" tilesize="512" devices="!androidstock|webgl">
      <level tiledimagewidth="2560" tiledimageheight="2560">
          <front url="center_4035/0/2/%v_%u.jpg"/>
          <right url="center_4035/1/2/%v_%u.jpg"/>
          <back  url="center_4035/2/2/%v_%u.jpg"/>
          <left  url="center_4035/3/2/%v_%u.jpg"/>
          <up    url="center_4035/4/2/%v_%u.jpg"/>
          <down  url="center_4035/5/2/%v_%u.jpg"/>
      </level>
      <level tiledimagewidth="1536" tiledimageheight="1536">
          <front url="center_4035/0/1/%v_%u.jpg"/>
          <right url="center_4035/1/1/%v_%u.jpg"/>
          <back  url="center_4035/2/1/%v_%u.jpg"/>
          <left  url="center_4035/3/1/%v_%u.jpg"/>
          <up    url="center_4035/4/1/%v_%u.jpg"/>
          <down  url="center_4035/5/1/%v_%u.jpg"/>
      </level>
      <level tiledimagewidth="1024" tiledimageheight="1024">
          <front url="center_4035/0/0/%v_%u.jpg"/>
          <right url="center_4035/1/0/%v_%u.jpg"/>
          <back  url="center_4035/2/0/%v_%u.jpg"/>
          <left  url="center_4035/3/0/%v_%u.jpg"/>
          <up    url="center_4035/4/0/%v_%u.jpg"/>
          <down  url="center_4035/5/0/%v_%u.jpg"/>
      </level>
    </image>
      <image type="CUBE" devices="androidstock.and.no-webgl">
        <front url="center_4035/mobile/0.jpg"/>
        <right url="center_4035/mobile/1.jpg"/>
        <back  url="center_4035/mobile/2.jpg"/>
        <left  url="center_4035/mobile/3.jpg"/>
        <up    url="center_4035/mobile/4.jpg"/>
        <down  url="center_4035/mobile/5.jpg"/>
      </image>








  <action name="setzorder2onstandardspots">
    if (device.html5,
      ifnot (device.desktop,


      );
    );
  </action>


</scene>



<!-- **** @PanoName="Right Corner" @PanoFile="/Users/ioannisexarchos/Desktop/Crowdhackathon VR /smartcity/Right Corner.jpg" **** -->
<!-- **** Width="6912px" Height="3456px" **** -->
<scene name="pano4045"
       heading="0"
       group="panogroup4049"
       thumburl="%FIRSTXML%/right_corner_4045/thumbnail.jpg"
       backgroundsound=""
       backgroundsoundloops="0"
       haspolygons="false"
       titleid="pano4045_title"
       descriptionid=""
       multires="true"
       planar="false"
       full360="true"
       video="false"
       seen="false">

    <autorotate horizon="0.000000" tofov="90.000000" waittime="1" speed="5"/>


    <panoview h="0.000000" v="0.000000" fov="90.000000" hmin="-180" hmax="180" vmin="-90" vmax="90" fovmax="90" />

    <view fisheye="0"
          limitview="range"
          hlookatmin="-180"
          hlookatmax="180"
          vlookatmin="-90"
          vlookatmax="90"
          maxpixelzoom="1.0"
          fovtype="VFOV"
          fovmax="90"
          fov="90.000000"
          hlookat="0.000000"
          vlookat="0.000000"/>

    <preview url="%FIRSTXML%/right_corner_4045/preview.jpg" type="CUBESTRIP" striporder="FRBLUD" />

    <image type="CUBE" multires="true" baseindex="0" tilesize="512" devices="!androidstock|webgl">
      <level tiledimagewidth="2560" tiledimageheight="2560">
          <front url="right_corner_4045/0/2/%v_%u.jpg"/>
          <right url="right_corner_4045/1/2/%v_%u.jpg"/>
          <back  url="right_corner_4045/2/2/%v_%u.jpg"/>
          <left  url="right_corner_4045/3/2/%v_%u.jpg"/>
          <up    url="right_corner_4045/4/2/%v_%u.jpg"/>
          <down  url="right_corner_4045/5/2/%v_%u.jpg"/>
      </level>
      <level tiledimagewidth="1536" tiledimageheight="1536">
          <front url="right_corner_4045/0/1/%v_%u.jpg"/>
          <right url="right_corner_4045/1/1/%v_%u.jpg"/>
          <back  url="right_corner_4045/2/1/%v_%u.jpg"/>
          <left  url="right_corner_4045/3/1/%v_%u.jpg"/>
          <up    url="right_corner_4045/4/1/%v_%u.jpg"/>
          <down  url="right_corner_4045/5/1/%v_%u.jpg"/>
      </level>
      <level tiledimagewidth="1024" tiledimageheight="1024">
          <front url="right_corner_4045/0/0/%v_%u.jpg"/>
          <right url="right_corner_4045/1/0/%v_%u.jpg"/>
          <back  url="right_corner_4045/2/0/%v_%u.jpg"/>
          <left  url="right_corner_4045/3/0/%v_%u.jpg"/>
          <up    url="right_corner_4045/4/0/%v_%u.jpg"/>
          <down  url="right_corner_4045/5/0/%v_%u.jpg"/>
      </level>
    </image>
      <image type="CUBE" devices="androidstock.and.no-webgl">
        <front url="right_corner_4045/mobile/0.jpg"/>
        <right url="right_corner_4045/mobile/1.jpg"/>
        <back  url="right_corner_4045/mobile/2.jpg"/>
        <left  url="right_corner_4045/mobile/3.jpg"/>
        <up    url="right_corner_4045/mobile/4.jpg"/>
        <down  url="right_corner_4045/mobile/5.jpg"/>
      </image>








  <action name="setzorder2onstandardspots">
    if (device.html5,
      ifnot (device.desktop,


      );
    );
  </action>


</scene>


  <!-- Group Elevetor Reception : 2 panoramas -->
  

<!-- **** @PanoName="Elevetor to 1 or 5A" @PanoFile="/Users/ioannisexarchos/Desktop/Crowdhackathon VR /smartcity/Elevetor to 1 or 5A.jpg" **** -->
<!-- **** Width="6912px" Height="3456px" **** -->
<scene name="pano4038"
       heading="0"
       group="panogroup4051"
       thumburl="%FIRSTXML%/elevetor_to_1_or_5a_4038/thumbnail.jpg"
       backgroundsound=""
       backgroundsoundloops="0"
       haspolygons="false"
       titleid="pano4038_title"
       descriptionid=""
       multires="true"
       planar="false"
       full360="true"
       video="false"
       seen="false">

    <autorotate horizon="0.000000" tofov="90.000000" waittime="1" speed="5"/>


    <panoview h="0.000000" v="0.000000" fov="90.000000" hmin="-180" hmax="180" vmin="-90" vmax="90" fovmax="90" />

    <view fisheye="0"
          limitview="range"
          hlookatmin="-180"
          hlookatmax="180"
          vlookatmin="-90"
          vlookatmax="90"
          maxpixelzoom="1.0"
          fovtype="VFOV"
          fovmax="90"
          fov="90.000000"
          hlookat="0.000000"
          vlookat="0.000000"/>

    <preview url="%FIRSTXML%/elevetor_to_1_or_5a_4038/preview.jpg" type="CUBESTRIP" striporder="FRBLUD" />

    <image type="CUBE" multires="true" baseindex="0" tilesize="512" devices="!androidstock|webgl">
      <level tiledimagewidth="2560" tiledimageheight="2560">
          <front url="elevetor_to_1_or_5a_4038/0/2/%v_%u.jpg"/>
          <right url="elevetor_to_1_or_5a_4038/1/2/%v_%u.jpg"/>
          <back  url="elevetor_to_1_or_5a_4038/2/2/%v_%u.jpg"/>
          <left  url="elevetor_to_1_or_5a_4038/3/2/%v_%u.jpg"/>
          <up    url="elevetor_to_1_or_5a_4038/4/2/%v_%u.jpg"/>
          <down  url="elevetor_to_1_or_5a_4038/5/2/%v_%u.jpg"/>
      </level>
      <level tiledimagewidth="1536" tiledimageheight="1536">
          <front url="elevetor_to_1_or_5a_4038/0/1/%v_%u.jpg"/>
          <right url="elevetor_to_1_or_5a_4038/1/1/%v_%u.jpg"/>
          <back  url="elevetor_to_1_or_5a_4038/2/1/%v_%u.jpg"/>
          <left  url="elevetor_to_1_or_5a_4038/3/1/%v_%u.jpg"/>
          <up    url="elevetor_to_1_or_5a_4038/4/1/%v_%u.jpg"/>
          <down  url="elevetor_to_1_or_5a_4038/5/1/%v_%u.jpg"/>
      </level>
      <level tiledimagewidth="1024" tiledimageheight="1024">
          <front url="elevetor_to_1_or_5a_4038/0/0/%v_%u.jpg"/>
          <right url="elevetor_to_1_or_5a_4038/1/0/%v_%u.jpg"/>
          <back  url="elevetor_to_1_or_5a_4038/2/0/%v_%u.jpg"/>
          <left  url="elevetor_to_1_or_5a_4038/3/0/%v_%u.jpg"/>
          <up    url="elevetor_to_1_or_5a_4038/4/0/%v_%u.jpg"/>
          <down  url="elevetor_to_1_or_5a_4038/5/0/%v_%u.jpg"/>
      </level>
    </image>
      <image type="CUBE" devices="androidstock.and.no-webgl">
        <front url="elevetor_to_1_or_5a_4038/mobile/0.jpg"/>
        <right url="elevetor_to_1_or_5a_4038/mobile/1.jpg"/>
        <back  url="elevetor_to_1_or_5a_4038/mobile/2.jpg"/>
        <left  url="elevetor_to_1_or_5a_4038/mobile/3.jpg"/>
        <up    url="elevetor_to_1_or_5a_4038/mobile/4.jpg"/>
        <down  url="elevetor_to_1_or_5a_4038/mobile/5.jpg"/>
      </image>








  <action name="setzorder2onstandardspots">
    if (device.html5,
      ifnot (device.desktop,


      );
    );
  </action>


</scene>



<!-- **** @PanoName="Reception Main" @PanoFile="/Users/ioannisexarchos/Desktop/Crowdhackathon VR /smartcity/Reception Main.jpg" **** -->
<!-- **** Width="6912px" Height="3456px" **** -->
<scene name="pano4044"
       heading="0"
       group="panogroup4051"
       thumburl="%FIRSTXML%/reception_main_4044/thumbnail.jpg"
       backgroundsound=""
       backgroundsoundloops="0"
       haspolygons="false"
       titleid="pano4044_title"
       descriptionid=""
       multires="true"
       planar="false"
       full360="true"
       video="false"
       seen="false">

    <autorotate horizon="0.000000" tofov="90.000000" waittime="1" speed="5"/>


    <panoview h="0.000000" v="0.000000" fov="90.000000" hmin="-180" hmax="180" vmin="-90" vmax="90" fovmax="90" />

    <view fisheye="0"
          limitview="range"
          hlookatmin="-180"
          hlookatmax="180"
          vlookatmin="-90"
          vlookatmax="90"
          maxpixelzoom="1.0"
          fovtype="VFOV"
          fovmax="90"
          fov="90.000000"
          hlookat="0.000000"
          vlookat="0.000000"/>

    <preview url="%FIRSTXML%/reception_main_4044/preview.jpg" type="CUBESTRIP" striporder="FRBLUD" />

    <image type="CUBE" multires="true" baseindex="0" tilesize="512" devices="!androidstock|webgl">
      <level tiledimagewidth="2560" tiledimageheight="2560">
          <front url="reception_main_4044/0/2/%v_%u.jpg"/>
          <right url="reception_main_4044/1/2/%v_%u.jpg"/>
          <back  url="reception_main_4044/2/2/%v_%u.jpg"/>
          <left  url="reception_main_4044/3/2/%v_%u.jpg"/>
          <up    url="reception_main_4044/4/2/%v_%u.jpg"/>
          <down  url="reception_main_4044/5/2/%v_%u.jpg"/>
      </level>
      <level tiledimagewidth="1536" tiledimageheight="1536">
          <front url="reception_main_4044/0/1/%v_%u.jpg"/>
          <right url="reception_main_4044/1/1/%v_%u.jpg"/>
          <back  url="reception_main_4044/2/1/%v_%u.jpg"/>
          <left  url="reception_main_4044/3/1/%v_%u.jpg"/>
          <up    url="reception_main_4044/4/1/%v_%u.jpg"/>
          <down  url="reception_main_4044/5/1/%v_%u.jpg"/>
      </level>
      <level tiledimagewidth="1024" tiledimageheight="1024">
          <front url="reception_main_4044/0/0/%v_%u.jpg"/>
          <right url="reception_main_4044/1/0/%v_%u.jpg"/>
          <back  url="reception_main_4044/2/0/%v_%u.jpg"/>
          <left  url="reception_main_4044/3/0/%v_%u.jpg"/>
          <up    url="reception_main_4044/4/0/%v_%u.jpg"/>
          <down  url="reception_main_4044/5/0/%v_%u.jpg"/>
      </level>
    </image>
      <image type="CUBE" devices="androidstock.and.no-webgl">
        <front url="reception_main_4044/mobile/0.jpg"/>
        <right url="reception_main_4044/mobile/1.jpg"/>
        <back  url="reception_main_4044/mobile/2.jpg"/>
        <left  url="reception_main_4044/mobile/3.jpg"/>
        <up    url="reception_main_4044/mobile/4.jpg"/>
        <down  url="reception_main_4044/mobile/5.jpg"/>
      </image>








  <action name="setzorder2onstandardspots">
    if (device.html5,
      ifnot (device.desktop,


      );
    );
  </action>


</scene>


  <!-- Group SNFCC : 2 panoramas -->
  

<!-- **** @PanoName="NationalOpera" @PanoFile="/Users/ioannisexarchos/Desktop/Crowdhackathon VR /smartcity/NationalOpera.jpg" **** -->
<!-- **** Width="6912px" Height="3456px" **** -->
<scene name="pano4041"
       heading="0"
       group="panogroup4054"
       thumburl="%FIRSTXML%/nationalopera_4041/thumbnail.jpg"
       backgroundsound=""
       backgroundsoundloops="0"
       haspolygons="false"
       titleid="pano4041_title"
       descriptionid=""
       multires="true"
       planar="false"
       full360="true"
       video="false"
       seen="false">

    <autorotate horizon="0.000000" tofov="90.000000" waittime="1" speed="5"/>


    <panoview h="0.000000" v="0.000000" fov="90.000000" hmin="-180" hmax="180" vmin="-90" vmax="90" fovmax="90" />

    <view fisheye="0"
          limitview="range"
          hlookatmin="-180"
          hlookatmax="180"
          vlookatmin="-90"
          vlookatmax="90"
          maxpixelzoom="1.0"
          fovtype="VFOV"
          fovmax="90"
          fov="90.000000"
          hlookat="0.000000"
          vlookat="0.000000"/>

    <preview url="%FIRSTXML%/nationalopera_4041/preview.jpg" type="CUBESTRIP" striporder="FRBLUD" />

    <image type="CUBE" multires="true" baseindex="0" tilesize="512" devices="!androidstock|webgl">
      <level tiledimagewidth="2560" tiledimageheight="2560">
          <front url="nationalopera_4041/0/2/%v_%u.jpg"/>
          <right url="nationalopera_4041/1/2/%v_%u.jpg"/>
          <back  url="nationalopera_4041/2/2/%v_%u.jpg"/>
          <left  url="nationalopera_4041/3/2/%v_%u.jpg"/>
          <up    url="nationalopera_4041/4/2/%v_%u.jpg"/>
          <down  url="nationalopera_4041/5/2/%v_%u.jpg"/>
      </level>
      <level tiledimagewidth="1536" tiledimageheight="1536">
          <front url="nationalopera_4041/0/1/%v_%u.jpg"/>
          <right url="nationalopera_4041/1/1/%v_%u.jpg"/>
          <back  url="nationalopera_4041/2/1/%v_%u.jpg"/>
          <left  url="nationalopera_4041/3/1/%v_%u.jpg"/>
          <up    url="nationalopera_4041/4/1/%v_%u.jpg"/>
          <down  url="nationalopera_4041/5/1/%v_%u.jpg"/>
      </level>
      <level tiledimagewidth="1024" tiledimageheight="1024">
          <front url="nationalopera_4041/0/0/%v_%u.jpg"/>
          <right url="nationalopera_4041/1/0/%v_%u.jpg"/>
          <back  url="nationalopera_4041/2/0/%v_%u.jpg"/>
          <left  url="nationalopera_4041/3/0/%v_%u.jpg"/>
          <up    url="nationalopera_4041/4/0/%v_%u.jpg"/>
          <down  url="nationalopera_4041/5/0/%v_%u.jpg"/>
      </level>
    </image>
      <image type="CUBE" devices="androidstock.and.no-webgl">
        <front url="nationalopera_4041/mobile/0.jpg"/>
        <right url="nationalopera_4041/mobile/1.jpg"/>
        <back  url="nationalopera_4041/mobile/2.jpg"/>
        <left  url="nationalopera_4041/mobile/3.jpg"/>
        <up    url="nationalopera_4041/mobile/4.jpg"/>
        <down  url="nationalopera_4041/mobile/5.jpg"/>
      </image>








  <!-- **** 1 Point Spots **** -->





  <hotspot name="spotpoint4096"
           ath="63.217158" atv="-3.870968"
           style="IconDefaultPointSpotStyle"
           tag="point"
           distorted="true"
           depth="1000"
           descriptionid=""
           onclick="onclickspotpoint4096"
           tooltip="spotpoint4096_tooltip"
           />
  <hotspot name="spotpoint4096" devices="flash" zorder="3"/>
  <hotspot name="spotpoint4096" devices="html5" zorder="3" zorder2="1"/>
  <action name="onclickspotpoint4096">
  
        mainloadscene(pano4036);


  </action>



  <action name="hidepanopointspots">
    set(hotspot[spotpoint4096].visible, false);
  </action>
  <action name="showpanopointspots">
    set(hotspot[spotpoint4096].visible, true);
  </action>
  <events name="pano4041stopanimatedspots" onremovepano="" />


  <action name="showpanospotsaction">
    if (tour_displayspots,
    showpanopointspots();




    );
  </action>
  <action name="hidepanospotsaction">
    hidepanopointspots();




  </action>

  <action name="setzorder2onstandardspots">
    if (device.html5,
      ifnot (device.desktop,


        set(hotspot[spotpoint4096].zorder2, %1);

      );
    );
  </action>


</scene>



<!-- **** @PanoName="SNFCC" @PanoFile="/Users/ioannisexarchos/Desktop/Crowdhackathon VR /smartcity/SNFCC.jpg" **** -->
<!-- **** Width="6912px" Height="3456px" **** -->
<scene name="pano4046"
       heading="0"
       group="panogroup4054"
       thumburl="%FIRSTXML%/snfcc_4046/thumbnail.jpg"
       backgroundsound=""
       backgroundsoundloops="0"
       haspolygons="false"
       titleid="pano4046_title"
       descriptionid=""
       multires="true"
       planar="false"
       full360="true"
       video="false"
       seen="false">

    <autorotate horizon="0.000000" tofov="90.000000" waittime="1" speed="5"/>


    <panoview h="0.000000" v="0.000000" fov="90.000000" hmin="-180" hmax="180" vmin="-90" vmax="90" fovmax="90" />

    <view fisheye="0"
          limitview="range"
          hlookatmin="-180"
          hlookatmax="180"
          vlookatmin="-90"
          vlookatmax="90"
          maxpixelzoom="1.0"
          fovtype="VFOV"
          fovmax="90"
          fov="90.000000"
          hlookat="0.000000"
          vlookat="0.000000"/>

    <preview url="%FIRSTXML%/snfcc_4046/preview.jpg" type="CUBESTRIP" striporder="FRBLUD" />

    <image type="CUBE" multires="true" baseindex="0" tilesize="512" devices="!androidstock|webgl">
      <level tiledimagewidth="2560" tiledimageheight="2560">
          <front url="snfcc_4046/0/2/%v_%u.jpg"/>
          <right url="snfcc_4046/1/2/%v_%u.jpg"/>
          <back  url="snfcc_4046/2/2/%v_%u.jpg"/>
          <left  url="snfcc_4046/3/2/%v_%u.jpg"/>
          <up    url="snfcc_4046/4/2/%v_%u.jpg"/>
          <down  url="snfcc_4046/5/2/%v_%u.jpg"/>
      </level>
      <level tiledimagewidth="1536" tiledimageheight="1536">
          <front url="snfcc_4046/0/1/%v_%u.jpg"/>
          <right url="snfcc_4046/1/1/%v_%u.jpg"/>
          <back  url="snfcc_4046/2/1/%v_%u.jpg"/>
          <left  url="snfcc_4046/3/1/%v_%u.jpg"/>
          <up    url="snfcc_4046/4/1/%v_%u.jpg"/>
          <down  url="snfcc_4046/5/1/%v_%u.jpg"/>
      </level>
      <level tiledimagewidth="1024" tiledimageheight="1024">
          <front url="snfcc_4046/0/0/%v_%u.jpg"/>
          <right url="snfcc_4046/1/0/%v_%u.jpg"/>
          <back  url="snfcc_4046/2/0/%v_%u.jpg"/>
          <left  url="snfcc_4046/3/0/%v_%u.jpg"/>
          <up    url="snfcc_4046/4/0/%v_%u.jpg"/>
          <down  url="snfcc_4046/5/0/%v_%u.jpg"/>
      </level>
    </image>
      <image type="CUBE" devices="androidstock.and.no-webgl">
        <front url="snfcc_4046/mobile/0.jpg"/>
        <right url="snfcc_4046/mobile/1.jpg"/>
        <back  url="snfcc_4046/mobile/2.jpg"/>
        <left  url="snfcc_4046/mobile/3.jpg"/>
        <up    url="snfcc_4046/mobile/4.jpg"/>
        <down  url="snfcc_4046/mobile/5.jpg"/>
      </image>








  <!-- **** 1 Point Spots **** -->





  <hotspot name="spotpoint4095"
           ath="-85.415550" atv="-12.580645"
           style="IconDefaultPointSpotStyle"
           tag="point"
           distorted="true"
           depth="1000"
           descriptionid=""
           onclick="onclickspotpoint4095"
           tooltip="spotpoint4095_tooltip"
           />
  <hotspot name="spotpoint4095" devices="flash" zorder="3"/>
  <hotspot name="spotpoint4095" devices="html5" zorder="3" zorder2="1"/>
  <action name="onclickspotpoint4095">
  
        mainloadscene(pano4041);


  </action>



  <action name="hidepanopointspots">
    set(hotspot[spotpoint4095].visible, false);
  </action>
  <action name="showpanopointspots">
    set(hotspot[spotpoint4095].visible, true);
  </action>
  <events name="pano4046stopanimatedspots" onremovepano="" />


  <action name="showpanospotsaction">
    if (tour_displayspots,
    showpanopointspots();




    );
  </action>
  <action name="hidepanospotsaction">
    hidepanopointspots();




  </action>

  <action name="setzorder2onstandardspots">
    if (device.html5,
      ifnot (device.desktop,


        set(hotspot[spotpoint4095].zorder2, %1);

      );
    );
  </action>


</scene>


  <!-- Group First Floor : 3 panoramas -->
  

<!-- **** @PanoName="First Floor" @PanoFile="/Users/ioannisexarchos/Desktop/Crowdhackathon VR /smartcity/First Floor.jpg" **** -->
<!-- **** Width="6912px" Height="3456px" **** -->
<scene name="pano4039"
       heading="0"
       group="panogroup4052"
       thumburl="%FIRSTXML%/first_floor_4039/thumbnail.jpg"
       backgroundsound=""
       backgroundsoundloops="0"
       haspolygons="false"
       titleid="pano4039_title"
       descriptionid=""
       multires="false"
       planar="false"
       full360="true"
       video="false"
       seen="false">

    <autorotate horizon="0.000000" tofov="90.000000" waittime="1" speed="5"/>


    <panoview h="0.000000" v="0.000000" fov="90.000000" hmin="-180" hmax="180" vmin="-90" vmax="90" fovmax="90" />

    <view fisheye="0"
          limitview="range"
          hlookatmin="-180"
          hlookatmax="180"
          vlookatmin="-90"
          vlookatmax="90"
          maxpixelzoom="1.0"
          fovtype="VFOV"
          fovmax="90"
          fov="90.000000"
          hlookat="0.000000"
          vlookat="0.000000"/>

    <preview url="%FIRSTXML%/first_floor_4039/preview.jpg" type="CUBESTRIP" striporder="FRBLUD" />

    <image type="CUBE" devices="desktop|html5">
      <front url="first_floor_4039/First_Floor_0.jpg"/>
      <right url="first_floor_4039/First_Floor_1.jpg"/>
      <back  url="first_floor_4039/First_Floor_2.jpg"/>
      <left  url="first_floor_4039/First_Floor_3.jpg"/>
      <up    url="first_floor_4039/First_Floor_4.jpg"/>
      <down  url="first_floor_4039/First_Floor_5.jpg"/>
    </image>

    <image type="CUBE" devices="tablet">
      <front url="first_floor_4039/tablet/0.jpg"/>
      <right url="first_floor_4039/tablet/1.jpg"/>
      <back  url="first_floor_4039/tablet/2.jpg"/>
      <left  url="first_floor_4039/tablet/3.jpg"/>
      <up    url="first_floor_4039/tablet/4.jpg"/>
      <down  url="first_floor_4039/tablet/5.jpg"/>
    </image>
    <image type="CUBE" devices="mobile">
      <front url="first_floor_4039/mobile/0.jpg"/>
      <right url="first_floor_4039/mobile/1.jpg"/>
      <back  url="first_floor_4039/mobile/2.jpg"/>
      <left  url="first_floor_4039/mobile/3.jpg"/>
      <up    url="first_floor_4039/mobile/4.jpg"/>
      <down  url="first_floor_4039/mobile/5.jpg"/>
    </image>

      <image type="CUBE" devices="androidstock.and.no-webgl">
        <front url="first_floor_4039/mobile/0.jpg"/>
        <right url="first_floor_4039/mobile/1.jpg"/>
        <back  url="first_floor_4039/mobile/2.jpg"/>
        <left  url="first_floor_4039/mobile/3.jpg"/>
        <up    url="first_floor_4039/mobile/4.jpg"/>
        <down  url="first_floor_4039/mobile/5.jpg"/>
      </image>








  <action name="setzorder2onstandardspots">
    if (device.html5,
      ifnot (device.desktop,


      );
    );
  </action>


</scene>



<!-- **** @PanoName="Meeting Room" @PanoFile="/Users/ioannisexarchos/Desktop/Crowdhackathon VR /smartcity/Meeting Room.jpg" **** -->
<!-- **** Width="6912px" Height="3456px" **** -->
<scene name="pano4040"
       heading="0"
       group="panogroup4052"
       thumburl="%FIRSTXML%/meeting_room_4040/thumbnail.jpg"
       backgroundsound=""
       backgroundsoundloops="0"
       haspolygons="false"
       titleid="pano4040_title"
       descriptionid=""
       multires="false"
       planar="false"
       full360="true"
       video="false"
       seen="false">

    <autorotate horizon="0.000000" tofov="90.000000" waittime="1" speed="5"/>


    <panoview h="0.000000" v="0.000000" fov="90.000000" hmin="-180" hmax="180" vmin="-90" vmax="90" fovmax="90" />

    <view fisheye="0"
          limitview="range"
          hlookatmin="-180"
          hlookatmax="180"
          vlookatmin="-90"
          vlookatmax="90"
          maxpixelzoom="1.0"
          fovtype="VFOV"
          fovmax="90"
          fov="90.000000"
          hlookat="0.000000"
          vlookat="0.000000"/>

    <preview url="%FIRSTXML%/meeting_room_4040/preview.jpg" type="CUBESTRIP" striporder="FRBLUD" />

    <image type="CUBE" devices="desktop|html5">
      <front url="meeting_room_4040/Meeting_Room_0.jpg"/>
      <right url="meeting_room_4040/Meeting_Room_1.jpg"/>
      <back  url="meeting_room_4040/Meeting_Room_2.jpg"/>
      <left  url="meeting_room_4040/Meeting_Room_3.jpg"/>
      <up    url="meeting_room_4040/Meeting_Room_4.jpg"/>
      <down  url="meeting_room_4040/Meeting_Room_5.jpg"/>
    </image>

    <image type="CUBE" devices="tablet">
      <front url="meeting_room_4040/tablet/0.jpg"/>
      <right url="meeting_room_4040/tablet/1.jpg"/>
      <back  url="meeting_room_4040/tablet/2.jpg"/>
      <left  url="meeting_room_4040/tablet/3.jpg"/>
      <up    url="meeting_room_4040/tablet/4.jpg"/>
      <down  url="meeting_room_4040/tablet/5.jpg"/>
    </image>
    <image type="CUBE" devices="mobile">
      <front url="meeting_room_4040/mobile/0.jpg"/>
      <right url="meeting_room_4040/mobile/1.jpg"/>
      <back  url="meeting_room_4040/mobile/2.jpg"/>
      <left  url="meeting_room_4040/mobile/3.jpg"/>
      <up    url="meeting_room_4040/mobile/4.jpg"/>
      <down  url="meeting_room_4040/mobile/5.jpg"/>
    </image>

      <image type="CUBE" devices="androidstock.and.no-webgl">
        <front url="meeting_room_4040/mobile/0.jpg"/>
        <right url="meeting_room_4040/mobile/1.jpg"/>
        <back  url="meeting_room_4040/mobile/2.jpg"/>
        <left  url="meeting_room_4040/mobile/3.jpg"/>
        <up    url="meeting_room_4040/mobile/4.jpg"/>
        <down  url="meeting_room_4040/mobile/5.jpg"/>
      </image>








  <action name="setzorder2onstandardspots">
    if (device.html5,
      ifnot (device.desktop,


      );
    );
  </action>


</scene>



<!-- **** @PanoName="1A" @PanoFile="/Users/ioannisexarchos/Desktop/Crowdhackathon VR /smartcity/1A.jpg" **** -->
<!-- **** Width="6912px" Height="3456px" **** -->
<scene name="pano4034"
       heading="0"
       group="panogroup4052"
       thumburl="%FIRSTXML%/_1a_4034/thumbnail.jpg"
       backgroundsound=""
       backgroundsoundloops="0"
       haspolygons="false"
       titleid="pano4034_title"
       descriptionid=""
       multires="false"
       planar="false"
       full360="true"
       video="false"
       seen="false">

    <autorotate horizon="0.000000" tofov="90.000000" waittime="1" speed="5"/>


    <panoview h="0.000000" v="0.000000" fov="90.000000" hmin="-180" hmax="180" vmin="-90" vmax="90" fovmax="90" />

    <view fisheye="0"
          limitview="range"
          hlookatmin="-180"
          hlookatmax="180"
          vlookatmin="-90"
          vlookatmax="90"
          maxpixelzoom="1.0"
          fovtype="VFOV"
          fovmax="90"
          fov="90.000000"
          hlookat="0.000000"
          vlookat="0.000000"/>

    <preview url="%FIRSTXML%/_1a_4034/preview.jpg" type="CUBESTRIP" striporder="FRBLUD" />

    <image type="CUBE" devices="desktop|html5">
      <front url="_1a_4034/_1A_0.jpg"/>
      <right url="_1a_4034/_1A_1.jpg"/>
      <back  url="_1a_4034/_1A_2.jpg"/>
      <left  url="_1a_4034/_1A_3.jpg"/>
      <up    url="_1a_4034/_1A_4.jpg"/>
      <down  url="_1a_4034/_1A_5.jpg"/>
    </image>

    <image type="CUBE" devices="tablet">
      <front url="_1a_4034/tablet/0.jpg"/>
      <right url="_1a_4034/tablet/1.jpg"/>
      <back  url="_1a_4034/tablet/2.jpg"/>
      <left  url="_1a_4034/tablet/3.jpg"/>
      <up    url="_1a_4034/tablet/4.jpg"/>
      <down  url="_1a_4034/tablet/5.jpg"/>
    </image>
    <image type="CUBE" devices="mobile">
      <front url="_1a_4034/mobile/0.jpg"/>
      <right url="_1a_4034/mobile/1.jpg"/>
      <back  url="_1a_4034/mobile/2.jpg"/>
      <left  url="_1a_4034/mobile/3.jpg"/>
      <up    url="_1a_4034/mobile/4.jpg"/>
      <down  url="_1a_4034/mobile/5.jpg"/>
    </image>

      <image type="CUBE" devices="androidstock.and.no-webgl">
        <front url="_1a_4034/mobile/0.jpg"/>
        <right url="_1a_4034/mobile/1.jpg"/>
        <back  url="_1a_4034/mobile/2.jpg"/>
        <left  url="_1a_4034/mobile/3.jpg"/>
        <up    url="_1a_4034/mobile/4.jpg"/>
        <down  url="_1a_4034/mobile/5.jpg"/>
      </image>








  <action name="setzorder2onstandardspots">
    if (device.html5,
      ifnot (device.desktop,


      );
    );
  </action>


</scene>


  <krpano nofullspherepanoavailable="false" />



</krpano>

